Metadata-Version: 1.0
Name: graph-distributions
Version: 0.1
Summary: Gaussian distributions
Home-page: UNKNOWN
Author: Sreekanth Pulakkatt
Author-email: email@gmail.com
License: UNKNOWN
Platform: UNKNOWN
